{
    "from": "mar / 5 / 2025",
    "title": "itty bitty 8-bit (birthday remix)",
    "desc": "if you haven't noticed already i do music too, but not as often. anyways this is my gift to all of you, because i would feel bad about getting gifts and not giving one back ok... hope u enjoy this new type of content and tell me if i should do more...<br/><br/>yes that is a bfdi reference on betpowo.github.io. yes it's real",
    "extra": "<hr /><h3>uncompressed, stationary version so you can look at everyone:</h3><br/><div style='text-align: center;' class='sub-board' ><img src='/images/gallery/itty-bitty-static.png' width='500' height='500' style='margin: auto; border-radius: 20px;' loading='lazy'/><br/><a target='_blank' href='/images/gallery/itty-bitty-static.png'><button style='--col: var(--col-main);'>direct</button></a></div>",
    "feat": [
        "betpo",
        "betty",
        "carlos",
        "charles",
        "daniel",
        "epiphany",
        "fish",
        "glib",
        "haven",
        "jasmine",
        "josephine",
        "kinne",
        "mae",
        "marco",
        "melissa",
        "nori",
        "pipit",
        "sadie",
        "sprout"
    ],
    "link": [
        [
            "tube",
            "https://youtu.be/b9bbPr2dpXA"
        ]
    ],
    "extension": "gif"
}